Metadata-Version: 2.1
Name: dtais
Version: 0.0.3
Summary: a test version of dtais, add img aug
Home-page: https://github.com/
Author: Lazarrt
Author-email: 
Classifier: Programming Language :: Python :: 3
Classifier: License :: OSI Approved :: MIT License
Classifier: Operating System :: OS Independent
